souvenir/__main__.py
souvenir/svutils.py
souvenir-1.0.2.dist-info/entry_points.txt
souvenir-1.0.2.dist-info/WHEEL
souvenir-1.0.2.dist-info/METADATA
souvenir-1.0.2.dist-info/RECORD
